verifai/__init__.py
verifai/exporter.py
verifai/instrumentation.py
verifai/wrappers/__init__.py
verifai/wrappers/anthropic.py
verifai/wrappers/openai.py
verifai_llm_sdk-0.2.2.dist-info/METADATA
verifai_llm_sdk-0.2.2.dist-info/WHEEL
verifai_llm_sdk-0.2.2.dist-info/top_level.txt
verifai_llm_sdk-0.2.2.dist-info/RECORD
