Metadata-Version: 2.4
Name: verifai-llm-sdk
Version: 0.2.2
Summary: VerifAI Python SDK for LLM tracing and evaluation
Home-page: https://github.com/verifai-ai/verifai-sdk
Author: VerifAI Contributors
Author-email: VerifAI Contributors <hello@verifai.dev>
License: Apache-2.0
Project-URL: Homepage, https://github.com/verifai-ai/verifai-sdk
Project-URL: Documentation, https://docs.verifai.dev
Project-URL: Repository, https://github.com/verifai-ai/verifai-sdk
Project-URL: Issues, https://github.com/verifai-ai/verifai-sdk/issues
Keywords: ai,llm,tracing,evaluation,observability,opentelemetry
Classifier: Development Status :: 4 - Beta
Classifier: Intended Audience :: Developers
Classifier: Programming Language :: Python :: 3.9
Classifier: Programming Language :: Python :: 3.10
Classifier: Programming Language :: Python :: 3.11
Classifier: Programming Language :: Python :: 3.12
Classifier: Topic :: Software Development :: Libraries :: Python Modules
Classifier: Topic :: Scientific/Engineering :: Artificial Intelligence
Requires-Python: >=3.9
Requires-Dist: requests>=2.31.0
Requires-Dist: openai>=1.0.0
Requires-Dist: opentelemetry-sdk>=1.20.0
Requires-Dist: opentelemetry-api>=1.20.0
Requires-Dist: opentelemetry-instrumentation>=0.41b0
Provides-Extra: openai
Requires-Dist: opentelemetry-instrumentation-openai>=0.1.0; extra == "openai"
Provides-Extra: langchain
Requires-Dist: opentelemetry-instrumentation-langchain>=0.1.0; extra == "langchain"
Provides-Extra: dev
Requires-Dist: pytest>=7.0.0; extra == "dev"
Requires-Dist: pytest-cov>=4.0.0; extra == "dev"
Requires-Dist: black>=23.0.0; extra == "dev"
Requires-Dist: ruff>=0.1.0; extra == "dev"
Dynamic: author
Dynamic: home-page
Dynamic: requires-python
